django_hide_herokuapp-0.2.dist-info/WHEEL
django_hide_herokuapp-0.2.dist-info/metadata.json
django_hide_herokuapp-0.2.dist-info/DESCRIPTION.rst
django_hide_herokuapp-0.2.dist-info/METADATA
django_hide_herokuapp-0.2.dist-info/RECORD
django_hide_herokuapp-0.2.dist-info/top_level.txt
hide_herokuapp/tests.py
hide_herokuapp/views.py
hide_herokuapp/urls.py
hide_herokuapp/__init__.py
hide_herokuapp/middleware.py
