Metadata-Version: 2.0
Name: django-hide-herokuapp
Version: 0.2
Summary: Direct search engines not to index *.herokuapp.com URLs.
Home-page: https://github.com/isms/django-hide-herokuapp/
Author: Isaac Slavitt
Author-email: isaac@drivendata.org
License: MIT License
Keywords: django,heroku,herokuapp
Platform: UNKNOWN
Classifier: Environment :: Web Environment
Classifier: Framework :: Django
Classifier: Intended Audience :: Developers
Classifier: License :: OSI Approved :: MIT License
Classifier: Operating System :: OS Independent
Classifier: Programming Language :: Python
Classifier: Topic :: Internet :: WWW/HTTP
Classifier: Topic :: Internet :: WWW/HTTP :: Dynamic Content
